ampere/__init__.py
ampere/app.py
ampere/app_shared.py
ampere/cache_plots.py
ampere/common.py
ampere/get_pypi_downloads.py
ampere/get_repo_metrics.py
ampere/mirror.py
ampere/models.py
ampere/styling.py
ampere/viz.py
ampere/api/__init__.py
ampere/api/limiter.py
ampere/api/main.py
ampere/api/routes/__init__.py
ampere/api/routes/downloads.py
ampere/api/routes/feed.py
ampere/api/routes/repos.py
ampere/assets/css/bootstrap.min.css
ampere/assets/css/style.css
ampere/assets/fonts/jetbrainsmonoregular.woff2
ampere/assets/js/plotly-basic-3.0.0-rc.2.min.js
ampere/assets/js/tooltip.js
ampere/cli/__init__.py
ampere/cli/app.py
ampere/cli/common.py
ampere/cli/models.py
ampere/cli/commands/downloads.py
ampere/cli/commands/feed.py
ampere/cli/commands/repos.py
ampere/dagster/__init__.py
ampere/dagster/assets.py
ampere/dagster/definitions.py
ampere/dagster/jobs.py
ampere/dagster/project.py
ampere/dagster/schedules.py
ampere/dagster/sensors.py
ampere/pages/about.py
ampere/pages/downloads.py
ampere/pages/feed.py
ampere/pages/issues.py
ampere/pages/network_followers.py
ampere/pages/network_stargazers.py
ampere/pages/status.py
ampere/pages/summary.py
ampere_meter-0.1.6.dist-info/METADATA
ampere_meter-0.1.6.dist-info/WHEEL
ampere_meter-0.1.6.dist-info/entry_points.txt
ampere_meter-0.1.6.dist-info/RECORD
