Metadata-Version: 2.4
Name: ampere-meter
Version: 0.1.6
Summary: Tooling to track and visualize engagement with the mrpowers-io organization
Author-email: Jeff Brennan <jeffbrennan10@gmail.com>
Requires-Python: <3.13,>=3.11
Requires-Dist: requests<3,>=2.32.3
Requires-Dist: sqlmodel<0.0.23,>=0.0.22
Requires-Dist: typer<0.16,>=0.15.1
Provides-Extra: api
Requires-Dist: fastapi[standard]<0.116,>=0.115.6; extra == 'api'
Requires-Dist: slowapi<0.2,>=0.1.9; extra == 'api'
Requires-Dist: uvicorn>=0.32.1; extra == 'api'
Provides-Extra: backend
Requires-Dist: dagster-dbt<0.26,>=0.25.3; extra == 'backend'
Requires-Dist: dagster-webserver<2,>=1.8.7; extra == 'backend'
Requires-Dist: dagster<2,>=1.8.7; extra == 'backend'
Requires-Dist: db-dtypes<2,>=1.3.0; extra == 'backend'
Requires-Dist: google-cloud-bigquery<4,>=3.26.0; extra == 'backend'
Provides-Extra: common
Requires-Dist: dbt-duckdb<2,>=1.9.0; extra == 'common'
Requires-Dist: deltalake<0.23,>=0.22.3; extra == 'common'
Requires-Dist: duckdb>=1.1.3; extra == 'common'
Requires-Dist: pandas<3,>=2.2.2; extra == 'common'
Requires-Dist: polars<2,>=1.7.1; extra == 'common'
Requires-Dist: python-dotenv<2,>=1.0.1; extra == 'common'
Provides-Extra: dev
Requires-Dist: pyright<2,>=1.1.380; extra == 'dev'
Requires-Dist: ruff-lsp<0.0.57,>=0.0.56; extra == 'dev'
Requires-Dist: shandy-sqlfmt[jinjafmt]<0.25,>=0.24.0; extra == 'dev'
Requires-Dist: sqlfluff<4,>=3.2.5; extra == 'dev'
Provides-Extra: viz
Requires-Dist: dash-bootstrap-components<2,>=1.6.0; extra == 'viz'
Requires-Dist: dash-breakpoints<0.2,>=0.1.0; extra == 'viz'
Requires-Dist: dash<3,>=2.18.1; extra == 'viz'
Requires-Dist: flask-caching<3,>=2.3.0; extra == 'viz'
Requires-Dist: flask-compress~=1.17; extra == 'viz'
Requires-Dist: gunicorn<24,>=23.0.0; extra == 'viz'
Requires-Dist: kaleido==0.2.1; extra == 'viz'
Requires-Dist: matplotlib<4,>=3.9.2; extra == 'viz'
Requires-Dist: plotly<6,>=5.24.1; extra == 'viz'
Requires-Dist: pypalettes<0.2,>=0.1.4; extra == 'viz'
Requires-Dist: scipy>=1.15.1; extra == 'viz'
